faessentials/__init__.py
faessentials/asset_formatter.py
faessentials/constants.py
faessentials/database.py
faessentials/global_logger.py
faessentials/security.py
faessentials/utils.py
faessentials/validators.py
fa_essentials-1.0.153.dist-info/LICENSE
fa_essentials-1.0.153.dist-info/METADATA
fa_essentials-1.0.153.dist-info/WHEEL
fa_essentials-1.0.153.dist-info/top_level.txt
fa_essentials-1.0.153.dist-info/RECORD
