Metadata-Version: 2.1
Name: fa-essentials
Version: 1.0.153
Summary: Essentials for our projects.
Author-email: Brayan <brayan@sparkandhale.com>
Project-URL: Homepage, https://github.com/Freya-Alpha/fa-essentials
Keywords: finance,trading,models
Classifier: License :: OSI Approved :: MIT License
Classifier: Programming Language :: Python
Requires-Python: >=3.9
License-File: LICENSE
Requires-Dist: redis
Requires-Dist: tomli ; python_version < "3.11"
Provides-Extra: dev
Requires-Dist: black ; extra == 'dev'
Requires-Dist: bumpver ; extra == 'dev'
Requires-Dist: isort ; extra == 'dev'
Requires-Dist: pip-tools ; extra == 'dev'
Requires-Dist: pytest ; extra == 'dev'
